dynapipe/__init__.py
dynapipe/autoCV.py
dynapipe/autoFS.py
dynapipe/autoPP.py
dynapipe/autoPipe.py
dynapipe/autoViz.py
dynapipe/estimatorCV.py
dynapipe/funcPP.py
dynapipe/parameters.json
dynapipe/reset_parameters.json
dynapipe/selectorFS.py
dynapipe/utilis_func.py
dynapipe-0.2.3.dist-info/LICENSE
dynapipe-0.2.3.dist-info/METADATA
dynapipe-0.2.3.dist-info/WHEEL
dynapipe-0.2.3.dist-info/top_level.txt
dynapipe-0.2.3.dist-info/RECORD
