Metadata-Version: 2.1
Name: dynapipe
Version: 0.2.3
Summary: Dynamic Pipeline is a high-level API to help data scientists building models in ensemble way, and automating Machine Learning workflow with simple coding.
Home-page: https://github.com/tonyleidong/DynamicPipeline
Author: Tony Dong
Author-email: tonyleidong@gmail.com
License: UNKNOWN
Keywords: auto machine learning,features selection,model selection,model preprocessing,pipeline cluster,pipeline cluster traversal experiments,ensemble pipelines
Platform: UNKNOWN
Classifier: Programming Language :: Python :: 3.8
Classifier: License :: OSI Approved :: MIT License
Classifier: Operating System :: OS Independent
Requires-Python: >=3.7
Requires-Dist: pandas
Requires-Dist: scikit-learn
Requires-Dist: statsmodels
Requires-Dist: scipy
Requires-Dist: joblib
Requires-Dist: category-encoders
Requires-Dist: plotly
